MANIFEST.in
README.md
setup.py
version.py
swaggerit/__init__.py
swaggerit/aiohttp_api.py
swaggerit/api.py
swaggerit/constants.py
swaggerit/exceptions.py
swaggerit/json_builder.py
swaggerit/method.py
swaggerit/request.py
swaggerit/response.py
swaggerit/swagger_schema_extended.json
swaggerit/swagger_template.json
swaggerit/utils.py
swaggerit.egg-info/PKG-INFO
swaggerit.egg-info/SOURCES.txt
swaggerit.egg-info/dependency_links.txt
swaggerit.egg-info/requires.txt
swaggerit.egg-info/top_level.txt
swaggerit/models/__init__.py
swaggerit/models/_base.py
swaggerit/models/_swaggerit_meta.py
swaggerit/models/swaggerit.py
swaggerit/models/orm/__init__.py
swaggerit/models/orm/_jobs_meta.py
swaggerit/models/orm/_redis_base.py
swaggerit/models/orm/_swaggerit_meta.py
swaggerit/models/orm/binds.py
swaggerit/models/orm/factory.py
swaggerit/models/orm/jobs.py
swaggerit/models/orm/redis_elsearch.py
swaggerit/models/orm/session.py
swaggerit/models/orm/sqlalchemy_redis.py
tests/__init__.py
tests/integration/__init__.py
tests/integration/conftest.py
tests/integration/fixtures.py
tests/integration/test_aiohttp_api.py
tests/integration/test_method_errors.py
tests/integration/models/__init__.py
tests/integration/models/orm/__init__.py
tests/integration/models/orm/fixtures.py
tests/integration/models/orm/test_jobs_integration.py
tests/integration/models/orm/test_redis_elsearch_integration.py
tests/integration/models/orm/test_session_integration.py
tests/integration/models/orm/test_session_without_redis_integration.py
tests/integration/models/orm/test_sqlalchemy_redis_get_integration.py
tests/integration/models/orm/test_sqlalchemy_redis_get_related_integration.py
tests/integration/models/orm/test_sqlalchemy_redis_integration.py
tests/unit/__init__.py
tests/unit/test_json_builder.py